rdiff_backup.libs/librsync-7a6f72b4.so.2.3.4
rdiff_backup-2.4.0.data/data/share/doc/rdiff-backup/migration.adoc
rdiff_backup-2.4.0.data/data/share/doc/rdiff-backup/Windows-DEVELOP.adoc
rdiff_backup-2.4.0.data/data/share/doc/rdiff-backup/CHANGELOG.adoc
rdiff_backup-2.4.0.data/data/share/doc/rdiff-backup/README.adoc
rdiff_backup-2.4.0.data/data/share/doc/rdiff-backup/Windows-README.adoc
rdiff_backup-2.4.0.data/data/share/doc/rdiff-backup/COPYING
rdiff_backup-2.4.0.data/data/share/doc/rdiff-backup/FAQ.adoc
rdiff_backup-2.4.0.data/data/share/doc/rdiff-backup/examples.adoc
rdiff_backup-2.4.0.data/data/share/doc/rdiff-backup/credits.adoc
rdiff_backup-2.4.0.data/data/share/doc/rdiff-backup/DEVELOP.adoc
rdiff_backup-2.4.0.data/data/share/man/man1/rdiff-backup-delete.1
rdiff_backup-2.4.0.data/data/share/man/man1/rdiff-backup-statistics.1
rdiff_backup-2.4.0.data/data/share/man/man1/rdiff-backup.1
rdiff_backup-2.4.0.data/data/share/bash-completion/completions/rdiff-backup
rdiff_backup/librsync.py
rdiff_backup/run_delete.py
rdiff_backup/selection.py
rdiff_backup/longname.py
rdiff_backup/manage.py
rdiff_backup/fs_abilities.py
rdiff_backup/SetConnections.py
rdiff_backup/win_acls.py
rdiff_backup/robust.py
rdiff_backup/FilenameMapping.py
rdiff_backup/statistics.py
rdiff_backup/rorpiter.py
rdiff_backup/Globals.py
rdiff_backup/iterfile.py
rdiff_backup/eas_acls.py
rdiff_backup/C.cpython-38-x86_64-linux-gnu.so
rdiff_backup/increment.py
rdiff_backup/_librsync.cpython-38-x86_64-linux-gnu.so
rdiff_backup/connection.py
rdiff_backup/__init__.py
rdiff_backup/Rdiff.py
rdiff_backup/log.py
rdiff_backup/regress.py
rdiff_backup/Hardlink.py
rdiff_backup/backup.py
rdiff_backup/rpath.py
rdiff_backup/restore.py
rdiff_backup/run_stats.py
rdiff_backup/Time.py
rdiff_backup/user_group.py
rdiff_backup/Security.py
rdiff_backup/compare.py
rdiff_backup/Main.py
rdiff_backup/hash.py
rdiffbackup/arguments.py
rdiffbackup/run.py
rdiffbackup/actions_mgr.py
rdiff_backup-2.4.0.dist-info/top_level.txt
rdiff_backup-2.4.0.dist-info/WHEEL
rdiff_backup-2.4.0.dist-info/RECORD
rdiff_backup-2.4.0.dist-info/METADATA
rdiff_backup-2.4.0.dist-info/COPYING
rdiff_backup-2.4.0.dist-info/entry_points.txt
