Metadata-Version: 2.1
Name: rdiff-backup
Version: 2.4.0
Summary: Backup and Restore utility, easy to use, efficient, locally and remotely usable
Home-page: https://rdiff-backup.net/
Download-URL: https://github.com/rdiff-backup/rdiff-backup/releases
Author: The rdiff-backup project
Author-email: rdiff-backup-users@nongnu.org
License: GPLv2+
Keywords: backup,simple,easy,remote,incremental,efficient,cross-platform
Platform: linux
Platform: win32
Classifier: Development Status :: 5 - Production/Stable
Classifier: Environment :: Console
Classifier: Intended Audience :: End Users/Desktop
Classifier: Intended Audience :: System Administrators
Classifier: License :: OSI Approved :: GNU General Public License v2 or later (GPLv2+)
Classifier: Natural Language :: English
Classifier: Operating System :: POSIX :: Linux
Classifier: Operating System :: POSIX
Classifier: Operating System :: Microsoft :: Windows
Classifier: Programming Language :: Python :: 3
Classifier: Topic :: System :: Archiving :: Backup
Requires-Python: ~=3.6
License-File: COPYING
Requires-Dist: PyYAML
Requires-Dist: pywin32 ; platform_system == "Windows"
Requires-Dist: importlib-metadata ; python_version < "3.8"
Provides-Extra: meta
Requires-Dist: psutil ; extra == 'meta'
Requires-Dist: pylibacl ; (os_name == "posix") and extra == 'meta'
Requires-Dist: pyxattr ; (platform_system == "Linux") and extra == 'meta'
